wave.v
module  modulo3 (dat_i,reminder);
 input   [ 7: 0] dat_i;
    output  [ 1: 0] reminder;
    wire    [ 1: 0] dat_1, dat_2, dat_3, dat_4;
    wire    [ 1: 0] dat_5, dat_6;
 
    type_conv TC0(
        .plus_one(dat_i[1]),
        .minus_one(dat_i[0]),
        .dat_o(dat_1)
    );
 
    type_conv TC1(
        .plus_one(dat_i[2]),
        .minus_one(dat_i[3]),
        .dat_o(dat_2)
    );
 
    type_conv TC2(
        .plus_one(dat_i[4]),
        .minus_one(dat_i[5]),
        .dat_o(dat_3)
    );
 
    type_conv TC3(
        .plus_one(dat_i[6]),
        .minus_one(dat_i[7]),
        .dat_o(dat_4)
    );    
 
    mod3_adder MA0(
        .din_a(dat_1), .din_b(dat_2),
        .dat_o(dat_5)
    );
 
    mod3_adder MA1(
        .din_a(dat_3), .din_b(dat_4),
        .dat_o(dat_6)
    );
 
    mod3_adder MA3(
        .din_a(dat_5), .din_b(dat_6),
        .dat_o(reminder)
    );
 
endmodule
//convert to signed data
module  type_conv (
    input   plus_one,
            minus_one,
    output  reg [ 1: 0] dat_o
    );
 
    always@(*)  begin
        case ({plus_one, minus_one})
            2'b00   :   dat_o   = 2'b00;
            2'b01   :   dat_o   = 2'b10;
            2'b10   :   dat_o   = 2'b01;
            2'b11   :   dat_o   = 2'b00;
            default :   dat_o   = 2'b00;
        endcase
    end
 
endmodule
 
//a qucik mod3 adder
module  mod3_adder (
    input   [ 1: 0] din_a, din_b,
    output  reg [ 1: 0] dat_o
    );
 
    always@(*)  begin
        case ({din_a, din_b})
            4'b00_00    :   dat_o   = 2'b00;
            4'b00_01    :   dat_o   = 2'b01;
            4'b00_10    :   dat_o   = 2'b10;
            4'b01_00    :   dat_o   = 2'b01;
            4'b01_01    :   dat_o   = 2'b10;
            4'b01_10    :   dat_o   = 2'b00;
            4'b10_00    :   dat_o   = 2'b10;
            4'b10_01    :   dat_o   = 2'b00;
            4'b10_10    :   dat_o   = 2'b01;
            default     :   dat_o   = 2'b00;
        endcase
    end
endmodule

wavetb.v
module  mod3_tb ();
    reg [ 7: 0] dat_i;
    reg [ 1: 0] comp;
    reg [ 1: 0] err_cnt;
 
    wire    [ 1: 0] reminder;
 
    initial begin
$dumpfile("test.vcd");
    		$dumpvars(0,mod3_tb);
        $display("------------------The self_check begin ------------------");
        dat_i   = 0;
        err_cnt = 0;
        repeat(256) begin
            comp    = dat_i % 3;
            #5;
            if (reminder != comp)   begin
                $display("comp = %d, calc data = %d", comp, reminder);
		
                err_cnt = err_cnt + 1;
            end
            dat_i   = dat_i + 1;
        end
 
        if (err_cnt == 0)
            $display("------------------The self_check passed------------------");
        else
            $display("------------------The self_check failed------------------");
        $stop;
 
    end
 
    modulo3 M0(
        .dat_i(dat_i),
        .reminder(reminder)
    );

endmodule

test.vcd
$date
	Thu Aug 25 14:45:46 2022
$end
$version
	Icarus Verilog
$end
$timescale
	1s
$end
$scope module mod3_tb $end
$var wire 2 ! reminder [1:0] $end
$var reg 2 " comp [1:0] $end
$var reg 8 # dat_i [7:0] $end
$var reg 2 $ err_cnt [1:0] $end
$scope module M0 $end
$var wire 8 % dat_i [7:0] $end
$var wire 2 & reminder [1:0] $end
$var wire 2 ' dat_6 [1:0] $end
$var wire 2 ( dat_5 [1:0] $end
$var wire 2 ) dat_4 [1:0] $end
$var wire 2 * dat_3 [1:0] $end
$var wire 2 + dat_2 [1:0] $end
$var wire 2 , dat_1 [1:0] $end
$scope module MA0 $end
$var wire 2 - din_b [1:0] $end
$var wire 2 . din_a [1:0] $end
$var reg 2 / dat_o [1:0] $end
$upscope $end
$scope module MA1 $end
$var wire 2 0 din_b [1:0] $end
$var wire 2 1 din_a [1:0] $end
$var reg 2 2 dat_o [1:0] $end
$upscope $end
$scope module MA3 $end
$var wire 2 3 din_a [1:0] $end
$var wire 2 4 din_b [1:0] $end
$var reg 2 5 dat_o [1:0] $end
$upscope $end
$scope module TC0 $end
$var wire 1 6 minus_one $end
$var wire 1 7 plus_one $end
$var reg 2 8 dat_o [1:0] $end
$upscope $end
$scope module TC1 $end
$var wire 1 9 minus_one $end
$var wire 1 : plus_one $end
$var reg 2 ; dat_o [1:0] $end
$upscope $end
$scope module TC2 $end
$var wire 1 < minus_one $end
$var wire 1 = plus_one $end
$var reg 2 > dat_o [1:0] $end
$upscope $end
$scope module TC3 $end
$var wire 1 ? minus_one $end
$var wire 1 @ plus_one $end
$var reg 2 A dat_o [1:0] $end
$upscope $end
$upscope $end
$upscope $end
$enddefinitions $end
#0
$dumpvars
b0 A
0@
0?
b0 >
0=
0<
b0 ;
0:
09
b0 8
07
06
b0 5
b0 4
b0 3
b0 2
b0 1
b0 0
b0 /
b0 .
b0 -
b0 ,
b0 +
b0 *
b0 )
b0 (
b0 '
b0 &
b0 %
b0 $
b0 #
b0 "
b0 !
$end
#5
b10 !
b10 &
b10 5
b10 (
b10 /
b10 3
b10 ,
b10 .
b10 8
16
b1 "
b1 #
b1 %
#10
b1 !
b1 &
b1 5
b1 (
b1 /
b1 3
b1 ,
b1 .
b1 8
17
06
b10 "
b10 #
b10 %
b1 $
#15
b0 !
b0 &
b0 5
b0 (
b0 /
b0 3
b0 ,
b0 .
b0 8
16
b0 "
b11 #
b11 %
b10 $
#20
b1 !
b1 &
b1 5
b1 (
b1 /
b1 3
b1 +
b1 -
b1 ;
07
06
1:
b1 "
b100 #
b100 %
#25
b0 !
b0 &
b0 5
b0 (
b0 /
b0 3
b10 ,
b10 .
b10 8
16
b10 "
b101 #
b101 %
#30
b10 !
b10 &
b10 5
b10 (
b10 /
b10 3
b1 ,
b1 .
b1 8
17
06
b0 "
b110 #
b110 %
b11 $
#35
b1 !
b1 &
b1 5
b1 (
b1 /
b1 3
b0 ,
b0 .
b0 8
16
b1 "
b111 #
b111 %
b0 $
#40
b10 !
b10 &
b10 5
b10 (
b10 /
b10 3
b10 +
b10 -
b10 ;
07
06
0:
19
b10 "
b1000 #
b1000 %
#45
b1 !
b1 &
b1 5
b1 (
b1 /
b1 3
b10 ,
b10 .
b10 8
16
b0 "
b1001 #
b1001 %
#50
b0 !
b0 &
b0 5
b0 (
b0 /
b0 3
b1 ,
b1 .
b1 8
17
06
b1 "
b1010 #
b1010 %
b1 $
#55
b10 !
b10 &
b10 5
b10 (
b10 /
b10 3
b0 ,
b0 .
b0 8
16
b10 "
b1011 #
b1011 %
b10 $
#60
b0 !
b0 &
b0 5
b0 (
b0 /
b0 3
b0 +
b0 -
b0 ;
07
06
1:
b0 "
b1100 #
b1100 %
#65
b10 !
b10 &
b10 5
b10 (
b10 /
b10 3
b10 ,
b10 .
b10 8
16
b1 "
b1101 #
b1101 %
#70
b1 !
b1 &
b1 5
b1 (
b1 /
b1 3
b1 ,
b1 .
b1 8
17
06
b10 "
b1110 #
b1110 %
b11 $
#75
b0 !
b0 &
b0 5
b0 (
b0 /
b0 3
b0 ,
b0 .
b0 8
16
b0 "
b1111 #
b1111 %
b0 $
#80
b1 !
b1 &
b1 5
b1 '
b1 2
b1 4
b1 *
b1 1
b1 >
07
06
0:
09
1=
b1 "
b10000 #
b10000 %
#85
b0 !
b0 &
b0 5
b10 (
b10 /
b10 3
b10 ,
b10 .
b10 8
16
b10 "
b10001 #
b10001 %
#90
b10 !
b10 &
b10 5
b1 (
b1 /
b1 3
b1 ,
b1 .
b1 8
17
06
b0 "
b10010 #
b10010 %
b1 $
#95
b1 !
b1 &
b1 5
b0 (
b0 /
b0 3
b0 ,
b0 .
b0 8
16
b1 "
b10011 #
b10011 %
b10 $
#100
b10 !
b10 &
b10 5
b1 (
b1 /
b1 3
b1 +
b1 -
b1 ;
07
06
1:
b10 "
b10100 #
b10100 %
#105
b1 !
b1 &
b1 5
b0 (
b0 /
b0 3
b10 ,
b10 .
b10 8
16
b0 "
b10101 #
b10101 %
#110
b0 !
b0 &
b0 5
b10 (
b10 /
b10 3
b1 ,
b1 .
b1 8
17
06
b1 "
b10110 #
b10110 %
b11 $
#115
b10 !
b10 &
b10 5
b1 (
b1 /
b1 3
b0 ,
b0 .
b0 8
16
b10 "
b10111 #
b10111 %
b0 $
#120
b0 !
b0 &
b0 5
b10 (
b10 /
b10 3
b10 +
b10 -
b10 ;
07
06
0:
19
b0 "
b11000 #
b11000 %
#125
b10 !
b10 &
b10 5
b1 (
b1 /
b1 3
b10 ,
b10 .
b10 8
16
b1 "
b11001 #
b11001 %
#130
b1 !
b1 &
b1 5
b0 (
b0 /
b0 3
b1 ,
b1 .
b1 8
17
06
b10 "
b11010 #
b11010 %
b1 $
#135
b0 !
b0 &
b0 5
b10 (
b10 /
b10 3
b0 ,
b0 .
b0 8
16
b0 "
b11011 #
b11011 %
b10 $
#140
b1 !
b1 &
b1 5
b0 (
b0 /
b0 3
b0 +
b0 -
b0 ;
07
06
1:
b1 "
b11100 #
b11100 %
#145
b0 !
b0 &
b0 5
b10 (
b10 /
b10 3
b10 ,
b10 .
b10 8
16
b10 "
b11101 #
b11101 %
#150
b10 !
b10 &
b10 5
b1 (
b1 /
b1 3
b1 ,
b1 .
b1 8
17
06
b0 "
b11110 #
b11110 %
b11 $
#155
b1 !
b1 &
b1 5
b0 (
b0 /
b0 3
b0 ,
b0 .
b0 8
16
b1 "
b11111 #
b11111 %
b0 $
#160
b10 !
b10 &
b10 5
b10 '
b10 2
b10 4
b10 *
b10 1
b10 >
07
06
0:
09
0=
1<
b10 "
b100000 #
b100000 %
#165
b1 !
b1 &
b1 5
b10 (
b10 /
b10 3
b10 ,
b10 .
b10 8
16
b0 "
b100001 #
b100001 %
#170
b0 !
b0 &
b0 5
b1 (
b1 /
b1 3
b1 ,
b1 .
b1 8
17
06
b1 "
b100010 #
b100010 %
b1 $
#175
b10 !
b10 &
b10 5
b0 (
b0 /
b0 3
b0 ,
b0 .
b0 8
16
b10 "
b100011 #
b100011 %
b10 $
#180
b0 !
b0 &
b0 5
b1 (
b1 /
b1 3
b1 +
b1 -
b1 ;
07
06
1:
b0 "
b100100 #
b100100 %
#185
b10 !
b10 &
b10 5
b0 (
b0 /
b0 3
b10 ,
b10 .
b10 8
16
b1 "
b100101 #
b100101 %
#190
b1 !
b1 &
b1 5
b10 (
b10 /
b10 3
b1 ,
b1 .
b1 8
17
06
b10 "
b100110 #
b100110 %
b11 $
#195
b0 !
b0 &
b0 5
b1 (
b1 /
b1 3
b0 ,
b0 .
b0 8
16
b0 "
b100111 #
b100111 %
b0 $
#200
b1 !
b1 &
b1 5
b10 (
b10 /
b10 3
b10 +
b10 -
b10 ;
07
06
0:
19
b1 "
b101000 #
b101000 %
#205
b0 !
b0 &
b0 5
b1 (
b1 /
b1 3
b10 ,
b10 .
b10 8
16
b10 "
b101001 #
b101001 %
#210
b10 !
b10 &
b10 5
b0 (
b0 /
b0 3
b1 ,
b1 .
b1 8
17
06
b0 "
b101010 #
b101010 %
b1 $
#215
b1 !
b1 &
b1 5
b10 (
b10 /
b10 3
b0 ,
b0 .
b0 8
16
b1 "
b101011 #
b101011 %
b10 $
#220
b10 !
b10 &
b10 5
b0 (
b0 /
b0 3
b0 +
b0 -
b0 ;
07
06
1:
b10 "
b101100 #
b101100 %
#225
b1 !
b1 &
b1 5
b10 (
b10 /
b10 3
b10 ,
b10 .
b10 8
16
b0 "
b101101 #
b101101 %
#230
b0 !
b0 &
b0 5
b1 (
b1 /
b1 3
b1 ,
b1 .
b1 8
17
06
b1 "
b101110 #
b101110 %
b11 $
#235
b10 !
b10 &
b10 5
b0 (
b0 /
b0 3
b0 ,
b0 .
b0 8
16
b10 "
b101111 #
b101111 %
b0 $
#240
b0 !
b0 &
b0 5
b0 '
b0 2
b0 4
b0 *
b0 1
b0 >
07
06
0:
09
1=
b0 "
b110000 #
b110000 %
#245
b10 !
b10 &
b10 5
b10 (
b10 /
b10 3
b10 ,
b10 .
b10 8
16
b1 "
b110001 #
b110001 %
#250
b1 !
b1 &
b1 5
b1 (
b1 /
b1 3
b1 ,
b1 .
b1 8
17
06
b10 "
b110010 #
b110010 %
b1 $
#255
b0 !
b0 &
b0 5
b0 (
b0 /
b0 3
b0 ,
b0 .
b0 8
16
b0 "
b110011 #
b110011 %
b10 $
#260
b1 !
b1 &
b1 5
b1 (
b1 /
b1 3
b1 +
b1 -
b1 ;
07
06
1:
b1 "
b110100 #
b110100 %
#265
b0 !
b0 &
b0 5
b0 (
b0 /
b0 3
b10 ,
b10 .
b10 8
16
b10 "
b110101 #
b110101 %
#270
b10 !
b10 &
b10 5
b10 (
b10 /
b10 3
b1 ,
b1 .
b1 8
17
06
b0 "
b110110 #
b110110 %
b11 $
#275
b1 !
b1 &
b1 5
b1 (
b1 /
b1 3
b0 ,
b0 .
b0 8
16
b1 "
b110111 #
b110111 %
b0 $
#280
b10 !
b10 &
b10 5
b10 (
b10 /
b10 3
b10 +
b10 -
b10 ;
07
06
0:
19
b10 "
b111000 #
b111000 %
#285
b1 !
b1 &
b1 5
b1 (
b1 /
b1 3
b10 ,
b10 .
b10 8
16
b0 "
b111001 #
b111001 %
#290
b0 !
b0 &
b0 5
b0 (
b0 /
b0 3
b1 ,
b1 .
b1 8
17
06
b1 "
b111010 #
b111010 %
b1 $
#295
b10 !
b10 &
b10 5
b10 (
b10 /
b10 3
b0 ,
b0 .
b0 8
16
b10 "
b111011 #
b111011 %
b10 $
#300
b0 !
b0 &
b0 5
b0 (
b0 /
b0 3
b0 +
b0 -
b0 ;
07
06
1:
b0 "
b111100 #
b111100 %
#305
b10 !
b10 &
b10 5
b10 (
b10 /
b10 3
b10 ,
b10 .
b10 8
16
b1 "
b111101 #
b111101 %
#310
b1 !
b1 &
b1 5
b1 (
b1 /
b1 3
b1 ,
b1 .
b1 8
17
06
b10 "
b111110 #
b111110 %
b11 $
#315
b0 !
b0 &
b0 5
b0 (
b0 /
b0 3
b0 ,
b0 .
b0 8
16
b0 "
b111111 #
b111111 %
b0 $
#320
b1 !
b1 &
b1 5
b1 '
b1 2
b1 4
b1 )
b1 0
b1 A
07
06
0:
09
0=
0<
1@
b1 "
b1000000 #
b1000000 %
#325
b0 !
b0 &
b0 5
b10 (
b10 /
b10 3
b10 ,
b10 .
b10 8
16
b10 "
b1000001 #
b1000001 %
#330
b10 !
b10 &
b10 5
b1 (
b1 /
b1 3
b1 ,
b1 .
b1 8
17
06
b0 "
b1000010 #
b1000010 %
b1 $
#335
b1 !
b1 &
b1 5
b0 (
b0 /
b0 3
b0 ,
b0 .
b0 8
16
b1 "
b1000011 #
b1000011 %
b10 $
#340
b10 !
b10 &
b10 5
b1 (
b1 /
b1 3
b1 +
b1 -
b1 ;
07
06
1:
b10 "
b1000100 #
b1000100 %
#345
b1 !
b1 &
b1 5
b0 (
b0 /
b0 3
b10 ,
b10 .
b10 8
16
b0 "
b1000101 #
b1000101 %
#350
b0 !
b0 &
b0 5
b10 (
b10 /
b10 3
b1 ,
b1 .
b1 8
17
06
b1 "
b1000110 #
b1000110 %
b11 $
#355
b10 !
b10 &
b10 5
b1 (
b1 /
b1 3
b0 ,
b0 .
b0 8
16
b10 "
b1000111 #
b1000111 %
b0 $
#360
b0 !
b0 &
b0 5
b10 (
b10 /
b10 3
b10 +
b10 -
b10 ;
07
06
0:
19
b0 "
b1001000 #
b1001000 %
#365
b10 !
b10 &
b10 5
b1 (
b1 /
b1 3
b10 ,
b10 .
b10 8
16
b1 "
b1001001 #
b1001001 %
#370
b1 !
b1 &
b1 5
b0 (
b0 /
b0 3
b1 ,
b1 .
b1 8
17
06
b10 "
b1001010 #
b1001010 %
b1 $
#375
b0 !
b0 &
b0 5
b10 (
b10 /
b10 3
b0 ,
b0 .
b0 8
16
b0 "
b1001011 #
b1001011 %
b10 $
#380
b1 !
b1 &
b1 5
b0 (
b0 /
b0 3
b0 +
b0 -
b0 ;
07
06
1:
b1 "
b1001100 #
b1001100 %
#385
b0 !
b0 &
b0 5
b10 (
b10 /
b10 3
b10 ,
b10 .
b10 8
16
b10 "
b1001101 #
b1001101 %
#390
b10 !
b10 &
b10 5
b1 (
b1 /
b1 3
b1 ,
b1 .
b1 8
17
06
b0 "
b1001110 #
b1001110 %
b11 $
#395
b1 !
b1 &
b1 5
b0 (
b0 /
b0 3
b0 ,
b0 .
b0 8
16
b1 "
b1001111 #
b1001111 %
b0 $
#400
b10 !
b10 &
b10 5
b10 '
b10 2
b10 4
b1 *
b1 1
b1 >
07
06
0:
09
1=
b10 "
b1010000 #
b1010000 %
#405
b1 !
b1 &
b1 5
b10 (
b10 /
b10 3
b10 ,
b10 .
b10 8
16
b0 "
b1010001 #
b1010001 %
#410
b0 !
b0 &
b0 5
b1 (
b1 /
b1 3
b1 ,
b1 .
b1 8
17
06
b1 "
b1010010 #
b1010010 %
b1 $
#415
b10 !
b10 &
b10 5
b0 (
b0 /
b0 3
b0 ,
b0 .
b0 8
16
b10 "
b1010011 #
b1010011 %
b10 $
#420
b0 !
b0 &
b0 5
b1 (
b1 /
b1 3
b1 +
b1 -
b1 ;
07
06
1:
b0 "
b1010100 #
b1010100 %
#425
b10 !
b10 &
b10 5
b0 (
b0 /
b0 3
b10 ,
b10 .
b10 8
16
b1 "
b1010101 #
b1010101 %
#430
b1 !
b1 &
b1 5
b10 (
b10 /
b10 3
b1 ,
b1 .
b1 8
17
06
b10 "
b1010110 #
b1010110 %
b11 $
#435
b0 !
b0 &
b0 5
b1 (
b1 /
b1 3
b0 ,
b0 .
b0 8
16
b0 "
b1010111 #
b1010111 %
b0 $
#440
b1 !
b1 &
b1 5
b10 (
b10 /
b10 3
b10 +
b10 -
b10 ;
07
06
0:
19
b1 "
b1011000 #
b1011000 %
#445
b0 !
b0 &
b0 5
b1 (
b1 /
b1 3
b10 ,
b10 .
b10 8
16
b10 "
b1011001 #
b1011001 %
#450
b10 !
b10 &
b10 5
b0 (
b0 /
b0 3
b1 ,
b1 .
b1 8
17
06
b0 "
b1011010 #
b1011010 %
b1 $
#455
b1 !
b1 &
b1 5
b10 (
b10 /
b10 3
b0 ,
b0 .
b0 8
16
b1 "
b1011011 #
b1011011 %
b10 $
#460
b10 !
b10 &
b10 5
b0 (
b0 /
b0 3
b0 +
b0 -
b0 ;
07
06
1:
b10 "
b1011100 #
b1011100 %
#465
b1 !
b1 &
b1 5
b10 (
b10 /
b10 3
b10 ,
b10 .
b10 8
16
b0 "
b1011101 #
b1011101 %
#470
b0 !
b0 &
b0 5
b1 (
b1 /
b1 3
b1 ,
b1 .
b1 8
17
06
b1 "
b1011110 #
b1011110 %
b11 $
#475
b10 !
b10 &
b10 5
b0 (
b0 /
b0 3
b0 ,
b0 .
b0 8
16
b10 "
b1011111 #
b1011111 %
b0 $
#480
b0 !
b0 &
b0 5
b0 '
b0 2
b0 4
b10 *
b10 1
b10 >
07
06
0:
09
0=
1<
b0 "
b1100000 #
b1100000 %
#485
b10 !
b10 &
b10 5
b10 (
b10 /
b10 3
b10 ,
b10 .
b10 8
16
b1 "
b1100001 #
b1100001 %
#490
b1 !
b1 &
b1 5
b1 (
b1 /
b1 3
b1 ,
b1 .
b1 8
17
06
b10 "
b1100010 #
b1100010 %
b1 $
#495
b0 !
b0 &
b0 5
b0 (
b0 /
b0 3
b0 ,
b0 .
b0 8
16
b0 "
b1100011 #
b1100011 %
b10 $
#500
b1 !
b1 &
b1 5
b1 (
b1 /
b1 3
b1 +
b1 -
b1 ;
07
06
1:
b1 "
b1100100 #
b1100100 %
#505
b0 !
b0 &
b0 5
b0 (
b0 /
b0 3
b10 ,
b10 .
b10 8
16
b10 "
b1100101 #
b1100101 %
#510
b10 !
b10 &
b10 5
b10 (
b10 /
b10 3
b1 ,
b1 .
b1 8
17
06
b0 "
b1100110 #
b1100110 %
b11 $
#515
b1 !
b1 &
b1 5
b1 (
b1 /
b1 3
b0 ,
b0 .
b0 8
16
b1 "
b1100111 #
b1100111 %
b0 $
#520
b10 !
b10 &
b10 5
b10 (
b10 /
b10 3
b10 +
b10 -
b10 ;
07
06
0:
19
b10 "
b1101000 #
b1101000 %
#525
b1 !
b1 &
b1 5
b1 (
b1 /
b1 3
b10 ,
b10 .
b10 8
16
b0 "
b1101001 #
b1101001 %
#530
b0 !
b0 &
b0 5
b0 (
b0 /
b0 3
b1 ,
b1 .
b1 8
17
06
b1 "
b1101010 #
b1101010 %
b1 $
#535
b10 !
b10 &
b10 5
b10 (
b10 /
b10 3
b0 ,
b0 .
b0 8
16
b10 "
b1101011 #
b1101011 %
b10 $
#540
b0 !
b0 &
b0 5
b0 (
b0 /
b0 3
b0 +
b0 -
b0 ;
07
06
1:
b0 "
b1101100 #
b1101100 %
#545
b10 !
b10 &
b10 5
b10 (
b10 /
b10 3
b10 ,
b10 .
b10 8
16
b1 "
b1101101 #
b1101101 %
#550
b1 !
b1 &
b1 5
b1 (
b1 /
b1 3
b1 ,
b1 .
b1 8
17
06
b10 "
b1101110 #
b1101110 %
b11 $
#555
b0 !
b0 &
b0 5
b0 (
b0 /
b0 3
b0 ,
b0 .
b0 8
16
b0 "
b1101111 #
b1101111 %
b0 $
#560
b1 !
b1 &
b1 5
b1 '
b1 2
b1 4
b0 *
b0 1
b0 >
07
06
0:
09
1=
b1 "
b1110000 #
b1110000 %
#565
b0 !
b0 &
b0 5
b10 (
b10 /
b10 3
b10 ,
b10 .
b10 8
16
b10 "
b1110001 #
b1110001 %
#570
b10 !
b10 &
b10 5
b1 (
b1 /
b1 3
b1 ,
b1 .
b1 8
17
06
b0 "
b1110010 #
b1110010 %
b1 $
#575
b1 !
b1 &
b1 5
b0 (
b0 /
b0 3
b0 ,
b0 .
b0 8
16
b1 "
b1110011 #
b1110011 %
b10 $
#580
b10 !
b10 &
b10 5
b1 (
b1 /
b1 3
b1 +
b1 -
b1 ;
07
06
1:
b10 "
b1110100 #
b1110100 %
#585
b1 !
b1 &
b1 5
b0 (
b0 /
b0 3
b10 ,
b10 .
b10 8
16
b0 "
b1110101 #
b1110101 %
#590
b0 !
b0 &
b0 5
b10 (
b10 /
b10 3
b1 ,
b1 .
b1 8
17
06
b1 "
b1110110 #
b1110110 %
b11 $
#595
b10 !
b10 &
b10 5
b1 (
b1 /
b1 3
b0 ,
b0 .
b0 8
16
b10 "
b1110111 #
b1110111 %
b0 $
#600
b0 !
b0 &
b0 5
b10 (
b10 /
b10 3
b10 +
b10 -
b10 ;
07
06
0:
19
b0 "
b1111000 #
b1111000 %
#605
b10 !
b10 &
b10 5
b1 (
b1 /
b1 3
b10 ,
b10 .
b10 8
16
b1 "
b1111001 #
b1111001 %
#610
b1 !
b1 &
b1 5
b0 (
b0 /
b0 3
b1 ,
b1 .
b1 8
17
06
b10 "
b1111010 #
b1111010 %
b1 $
#615
b0 !
b0 &
b0 5
b10 (
b10 /
b10 3
b0 ,
b0 .
b0 8
16
b0 "
b1111011 #
b1111011 %
b10 $
#620
b1 !
b1 &
b1 5
b0 (
b0 /
b0 3
b0 +
b0 -
b0 ;
07
06
1:
b1 "
b1111100 #
b1111100 %
#625
b0 !
b0 &
b0 5
b10 (
b10 /
b10 3
b10 ,
b10 .
b10 8
16
b10 "
b1111101 #
b1111101 %
#630
b10 !
b10 &
b10 5
b1 (
b1 /
b1 3
b1 ,
b1 .
b1 8
17
06
b0 "
b1111110 #
b1111110 %
b11 $
#635
b1 !
b1 &
b1 5
b0 (
b0 /
b0 3
b0 ,
b0 .
b0 8
16
b1 "
b1111111 #
b1111111 %
b0 $
#640
b10 !
b10 &
b10 5
b10 '
b10 2
b10 4
b10 )
b10 0
b10 A
07
06
0:
09
0=
0<
0@
1?
b10 "
b10000000 #
b10000000 %
#645
b1 !
b1 &
b1 5
b10 (
b10 /
b10 3
b10 ,
b10 .
b10 8
16
b0 "
b10000001 #
b10000001 %
#650
b0 !
b0 &
b0 5
b1 (
b1 /
b1 3
b1 ,
b1 .
b1 8
17
06
b1 "
b10000010 #
b10000010 %
b1 $
#655
b10 !
b10 &
b10 5
b0 (
b0 /
b0 3
b0 ,
b0 .
b0 8
16
b10 "
b10000011 #
b10000011 %
b10 $
#660
b0 !
b0 &
b0 5
b1 (
b1 /
b1 3
b1 +
b1 -
b1 ;
07
06
1:
b0 "
b10000100 #
b10000100 %
#665
b10 !
b10 &
b10 5
b0 (
b0 /
b0 3
b10 ,
b10 .
b10 8
16
b1 "
b10000101 #
b10000101 %
#670
b1 !
b1 &
b1 5
b10 (
b10 /
b10 3
b1 ,
b1 .
b1 8
17
06
b10 "
b10000110 #
b10000110 %
b11 $
#675
b0 !
b0 &
b0 5
b1 (
b1 /
b1 3
b0 ,
b0 .
b0 8
16
b0 "
b10000111 #
b10000111 %
b0 $
#680
b1 !
b1 &
b1 5
b10 (
b10 /
b10 3
b10 +
b10 -
b10 ;
07
06
0:
19
b1 "
b10001000 #
b10001000 %
#685
b0 !
b0 &
b0 5
b1 (
b1 /
b1 3
b10 ,
b10 .
b10 8
16
b10 "
b10001001 #
b10001001 %
#690
b10 !
b10 &
b10 5
b0 (
b0 /
b0 3
b1 ,
b1 .
b1 8
17
06
b0 "
b10001010 #
b10001010 %
b1 $
#695
b1 !
b1 &
b1 5
b10 (
b10 /
b10 3
b0 ,
b0 .
b0 8
16
b1 "
b10001011 #
b10001011 %
b10 $
#700
b10 !
b10 &
b10 5
b0 (
b0 /
b0 3
b0 +
b0 -
b0 ;
07
06
1:
b10 "
b10001100 #
b10001100 %
#705
b1 !
b1 &
b1 5
b10 (
b10 /
b10 3
b10 ,
b10 .
b10 8
16
b0 "
b10001101 #
b10001101 %
#710
b0 !
b0 &
b0 5
b1 (
b1 /
b1 3
b1 ,
b1 .
b1 8
17
06
b1 "
b10001110 #
b10001110 %
b11 $
#715
b10 !
b10 &
b10 5
b0 (
b0 /
b0 3
b0 ,
b0 .
b0 8
16
b10 "
b10001111 #
b10001111 %
b0 $
#720
b0 !
b0 &
b0 5
b0 '
b0 2
b0 4
b1 *
b1 1
b1 >
07
06
0:
09
1=
b0 "
b10010000 #
b10010000 %
#725
b10 !
b10 &
b10 5
b10 (
b10 /
b10 3
b10 ,
b10 .
b10 8
16
b1 "
b10010001 #
b10010001 %
#730
b1 !
b1 &
b1 5
b1 (
b1 /
b1 3
b1 ,
b1 .
b1 8
17
06
b10 "
b10010010 #
b10010010 %
b1 $
#735
b0 !
b0 &
b0 5
b0 (
b0 /
b0 3
b0 ,
b0 .
b0 8
16
b0 "
b10010011 #
b10010011 %
b10 $
#740
b1 !
b1 &
b1 5
b1 (
b1 /
b1 3
b1 +
b1 -
b1 ;
07
06
1:
b1 "
b10010100 #
b10010100 %
#745
b0 !
b0 &
b0 5
b0 (
b0 /
b0 3
b10 ,
b10 .
b10 8
16
b10 "
b10010101 #
b10010101 %
#750
b10 !
b10 &
b10 5
b10 (
b10 /
b10 3
b1 ,
b1 .
b1 8
17
06
b0 "
b10010110 #
b10010110 %
b11 $
#755
b1 !
b1 &
b1 5
b1 (
b1 /
b1 3
b0 ,
b0 .
b0 8
16
b1 "
b10010111 #
b10010111 %
b0 $
#760
b10 !
b10 &
b10 5
b10 (
b10 /
b10 3
b10 +
b10 -
b10 ;
07
06
0:
19
b10 "
b10011000 #
b10011000 %
#765
b1 !
b1 &
b1 5
b1 (
b1 /
b1 3
b10 ,
b10 .
b10 8
16
b0 "
b10011001 #
b10011001 %
#770
b0 !
b0 &
b0 5
b0 (
b0 /
b0 3
b1 ,
b1 .
b1 8
17
06
b1 "
b10011010 #
b10011010 %
b1 $
#775
b10 !
b10 &
b10 5
b10 (
b10 /
b10 3
b0 ,
b0 .
b0 8
16
b10 "
b10011011 #
b10011011 %
b10 $
#780
b0 !
b0 &
b0 5
b0 (
b0 /
b0 3
b0 +
b0 -
b0 ;
07
06
1:
b0 "
b10011100 #
b10011100 %
#785
b10 !
b10 &
b10 5
b10 (
b10 /
b10 3
b10 ,
b10 .
b10 8
16
b1 "
b10011101 #
b10011101 %
#790
b1 !
b1 &
b1 5
b1 (
b1 /
b1 3
b1 ,
b1 .
b1 8
17
06
b10 "
b10011110 #
b10011110 %
b11 $
#795
b0 !
b0 &
b0 5
b0 (
b0 /
b0 3
b0 ,
b0 .
b0 8
16
b0 "
b10011111 #
b10011111 %
b0 $
#800
b1 !
b1 &
b1 5
b1 '
b1 2
b1 4
b10 *
b10 1
b10 >
07
06
0:
09
0=
1<
b1 "
b10100000 #
b10100000 %
#805
b0 !
b0 &
b0 5
b10 (
b10 /
b10 3
b10 ,
b10 .
b10 8
16
b10 "
b10100001 #
b10100001 %
#810
b10 !
b10 &
b10 5
b1 (
b1 /
b1 3
b1 ,
b1 .
b1 8
17
06
b0 "
b10100010 #
b10100010 %
b1 $
#815
b1 !
b1 &
b1 5
b0 (
b0 /
b0 3
b0 ,
b0 .
b0 8
16
b1 "
b10100011 #
b10100011 %
b10 $
#820
b10 !
b10 &
b10 5
b1 (
b1 /
b1 3
b1 +
b1 -
b1 ;
07
06
1:
b10 "
b10100100 #
b10100100 %
#825
b1 !
b1 &
b1 5
b0 (
b0 /
b0 3
b10 ,
b10 .
b10 8
16
b0 "
b10100101 #
b10100101 %
#830
b0 !
b0 &
b0 5
b10 (
b10 /
b10 3
b1 ,
b1 .
b1 8
17
06
b1 "
b10100110 #
b10100110 %
b11 $
#835
b10 !
b10 &
b10 5
b1 (
b1 /
b1 3
b0 ,
b0 .
b0 8
16
b10 "
b10100111 #
b10100111 %
b0 $
#840
b0 !
b0 &
b0 5
b10 (
b10 /
b10 3
b10 +
b10 -
b10 ;
07
06
0:
19
b0 "
b10101000 #
b10101000 %
#845
b10 !
b10 &
b10 5
b1 (
b1 /
b1 3
b10 ,
b10 .
b10 8
16
b1 "
b10101001 #
b10101001 %
